{
    "fish": [
        {
            "name": "GOLDFISH",
            "baitPreference": {
                "WORM": 1,
                "GRUB": 1,
                "SHRIMP": 0,
                "MEAT": 0
            },
            "activeHours": [0, 23],
            "habitats": ["BEGINNER"],
            "ratio": 10,
            "value": 1
        },
        {
            "name": "GUPPY",
            "baitPreference": {
                "WORM": 1,
                "GRUB": 1,
                "SHRIMP": 0,
                "MEAT": 0
            },
            "activeHours": [0, 23],
            "habitats": ["BEGINNER"],
            "ratio": 10,
            "value": 1
        },
        {
            "name": "EEL",
            "baitPreference": {
                "WORM": 1,
                "GRUB": 1,
                "SHRIMP": 0,
                "MEAT": 0
            },
            "activeHours": [0, 23],
            "habitats": ["BEGINNER"],
            "ratio": 10,
            "value": 6
        },
        {
            "name": "LOBSTER",
            "baitPreference": {
                "WORM": 1,
                "GRUB": 1,
                "SHRIMP": 0,
                "MEAT": 0
            },
            "activeHours": [0, 23],
            "habitats": ["BEGINNER"],
            "ratio": 10,
            "value": 20
        },
        {
            "name": "SHARK",
            "baitPreference": {
                "WORM": 1,
                "GRUB": 0,
                "SHRIMP": 0,
                "MEAT": 1
            },
            "activeHours": [5, 19],
            "habitats": ["BEGINNER", "OCEAN_ISLAND"],
            "ratio": 10,
            "value": 100
        }
    ]
}
